MANIFEST.in
README.rst
pyproject.toml
setup.py
pytep/__init__.py
pytep/engineutils.py
pytep/matlab_bridge.py
pytep/siminterface.py
pytep.egg-info/PKG-INFO
pytep.egg-info/SOURCES.txt
pytep.egg-info/dependency_links.txt
pytep.egg-info/requires.txt
pytep.egg-info/top_level.txt
pytep/setupinfo/idv_labels.pkl
pytep/setupinfo/process_var_labels.pkl
pytep/setupinfo/process_var_units.pkl
pytep/setupinfo/setpoint_labels.pkl
pytep/setupinfo/xmv_labels.pkl
pytep/setupinfo/xmv_units.pkl
pytep/simulator/Backup_MultiLoop_mode3.mdl
pytep/simulator/MultiLoop_mode3.mdl
pytep/simulator/MultiLoop_mode3.slxc
pytep/simulator/MultiLoop_mode3_R2019a.mdl
pytep/simulator/README.txt
pytep/simulator/TElib.mdl
pytep/simulator/TElib.mdl.r13
pytep/simulator/TElib_R2019a.mdl
pytep/simulator/__init__.py
pytep/simulator/temexd_mod.c
pytep/simulator/temexd_mod.mexa64
pytep/simulator/temexd_mod.mexw64
pytep/simulator/teprob_mod.h
pytep/simulator/tesys.mdl
pytep/simulator/tesys_R2019a.mdl
pytep/simulator/time_simrun.m
pytep/simulator/notforpytep/Mode_1_Init.m
pytep/simulator/notforpytep/TEplot.m
pytep/simulator/notforpytep/bridge_test.m
pytep/simulator/notforpytep/test_newInitStart.m
pytep/simulator/notforpytep/test_restartduringramp.m
pytep/simulator/notforpytep/test_simrestart.m
pytep/simulator/setupfiles/PV_LABELSANDUNITS.mat
pytep/simulator/setupfiles/SETPOINT_NAMES.mat
pytep/simulator/setupfiles/__init__.py
pytep/simulator/setupfiles/mode_one.mat
pytep/simulator/simcommands/__init__.py
pytep/simulator/simcommands/continue_simulation.m
pytep/simulator/simcommands/get_idv_input_block_params.m
pytep/simulator/simcommands/get_simulation_status.m
pytep/simulator/simcommands/get_sp_generic.m
pytep/simulator/simcommands/init_idvinput_from_workspace.m
pytep/simulator/simcommands/init_setpointinput_from_workspace.m
pytep/simulator/simcommands/isolate_recent_data_in_workspace.m
pytep/simulator/simcommands/loadSimEnvironment.m
pytep/simulator/simcommands/pause_simulation.m
pytep/simulator/simcommands/saveSimulationState.m
pytep/simulator/simcommands/set_idv_input_block_params.m
pytep/simulator/simcommands/set_simpause_time.m
