Metadata-Version: 2.1
Name: pytep
Version: 0.0.2
Summary: Tennessee Eastman simulator
Home-page: https://github.com/ChristopherReinartz/pytep.git
Author: Christopher Reinartz, Thomas Enevoldsen
Author-email: ccrein@elektro.dtu.dk
License: UNKNOWN
Download-URL: https://github.com/ChristopherReinartz/pytep/archive/refs/tags/v0.0.2.tar.gz
Platform: UNKNOWN
Classifier: Programming Language :: Python :: 3
Classifier: License :: OSI Approved :: BSD License
Classifier: Operating System :: OS Independent
Requires-Python: ==3.7.*
